remilia/__init__.py
remilia/__main__.py
remilia/config.py
remilia/log.py
remilia/plugins/Gua64/Gua64.py
remilia/plugins/Gua64/__init__.py
remilia/plugins/block/__init__.py
remilia/plugins/chat/__init__.py
remilia/plugins/chat/looklike.py
remilia/plugins/chat/resource/data.json
remilia/plugins/chat/utils.py
remilia/plugins/cmd/__init__.py
remilia/plugins/cmd/sys_cmd.py
remilia/plugins/code_runner/__init__.py
remilia/plugins/code_runner/data_source.py
remilia/plugins/setu/__init__.py
remilia/plugins/setu/acggov.py
remilia/plugins/setu/download.py
remilia/plugins/setu/lolicon.py
remilia/plugins/start/__init__.py
remilia/plugins/status/__init__.py
remilia/plugins/status/data_source.py
remilia_bot-0.3.0.dist-info/LICENSE
remilia_bot-0.3.0.dist-info/METADATA
remilia_bot-0.3.0.dist-info/WHEEL
remilia_bot-0.3.0.dist-info/entry_points.txt
remilia_bot-0.3.0.dist-info/RECORD
