Metadata-Version: 2.1
Name: remilia-bot
Version: 0.3.0
Summary: 女生自用(?)电报机器人
Home-page: https://github.com/tkgs0/RemiliaBot
License: GPL-3.0
Keywords: RemiliaBot,Telegram Bot,Telegram
Author: 月ヶ瀬
Requires-Python: >=3.9,<4.0
Classifier: License :: OSI Approved :: GNU General Public License v3 (GPLv3)
Classifier: Programming Language :: Python :: 3
Classifier: Programming Language :: Python :: 3.9
Classifier: Programming Language :: Python :: 3.10
Classifier: Programming Language :: Python :: 3.11
Requires-Dist: apscheduler (>=3.9.1.post1)
Requires-Dist: loguru (>=0.6.0)
Requires-Dist: psutil (>=5.9.0)
Requires-Dist: pydantic (>=1.10.0,<2.0.0,!=1.10.3)
Requires-Dist: python-telegram-bot (>=20.0)
Requires-Dist: pyyaml (>=6.0)
Requires-Dist: ujson (>=5.2.0)
Project-URL: Repository, https://github.com/tkgs0/RemiliaBot
